stackit/observability/__init__.py
stackit/observability/api/__init__.py
stackit/observability/api/default_api.py
stackit/observability/api_client.py
stackit/observability/api_response.py
stackit/observability/configuration.py
stackit/observability/exceptions.py
stackit/observability/models/__init__.py
stackit/observability/models/alert.py
stackit/observability/models/alert_config_receivers_response.py
stackit/observability/models/alert_config_route_response.py
stackit/observability/models/alert_group.py
stackit/observability/models/alert_group_response.py
stackit/observability/models/alert_groups_response.py
stackit/observability/models/alert_rule.py
stackit/observability/models/alert_rule_record.py
stackit/observability/models/alert_rules_response.py
stackit/observability/models/basic_auth.py
stackit/observability/models/cert_check_child_response.py
stackit/observability/models/cert_check_response.py
stackit/observability/models/create_alert_config_receiver_payload.py
stackit/observability/models/create_alert_config_receiver_payload_email_configs_inner.py
stackit/observability/models/create_alert_config_receiver_payload_opsgenie_configs_inner.py
stackit/observability/models/create_alert_config_receiver_payload_web_hook_configs_inner.py
stackit/observability/models/create_alert_config_route_payload.py
stackit/observability/models/create_alert_config_route_payload_routes_inner.py
stackit/observability/models/create_alertgroups_payload.py
stackit/observability/models/create_alertrules_payload.py
stackit/observability/models/create_cert_check400_response.py
stackit/observability/models/create_cert_check_payload.py
stackit/observability/models/create_credentials_payload.py
stackit/observability/models/create_credentials_response.py
stackit/observability/models/create_http_check_payload.py
stackit/observability/models/create_instance_payload.py
stackit/observability/models/create_instance_response.py
stackit/observability/models/create_logs_alertgroups_payload.py
stackit_observability-0.12.0.dist-info/METADATA
stackit_observability-0.12.0.dist-info/WHEEL
stackit_observability-0.12.0.dist-info/licenses/LICENSE.md
stackit_observability-0.12.0.dist-info/licenses/NOTICE.txt
stackit_observability-0.12.0.dist-info/RECORD
